imaginaryNLP/ImaginaryEmbeddings.py
imaginaryNLP/ImaginaryEmbeddingsForLTP.py
imaginaryNLP/ImaginaryEmbeddingsForSTP.py
imaginaryNLP/ImaginaryEmbeddingsForSequenceModeling.py
imaginaryNLP/__init__.py
imaginaryNLP/trainer.py
imaginaryNLP-0.0.4.dist-info/LICENSE
imaginaryNLP-0.0.4.dist-info/METADATA
imaginaryNLP-0.0.4.dist-info/WHEEL
imaginaryNLP-0.0.4.dist-info/top_level.txt
imaginaryNLP-0.0.4.dist-info/RECORD
