Metadata-Version: 2.1
Name: imaginaryNLP
Version: 0.0.4
Summary: Imaginary Embeddings for NLP
Download-URL: https://github.com/Justus-Jonas/imaginaryNLP
Author: Justus-Jonas Erker
Author-email: j.erker@student.maastrichtuniversity.nl
License: Apache License 2.0
Keywords: PyTorch NLP deep learning Imaginary Embeddings Dialog Systems
Classifier: Development Status :: 1 - Planning
Classifier: License :: OSI Approved :: Apache Software License
Classifier: Programming Language :: Python :: 3.6
Classifier: Topic :: Scientific/Engineering :: Artificial Intelligence
Classifier: Intended Audience :: Science/Research
Requires-Python: >=3.6.0
License-File: LICENSE
Requires-Dist: datasets (==2.13.1)
Requires-Dist: transformers (>=2.0.0)
Requires-Dist: torch (==2.0.1)
Requires-Dist: numpy (==1.21.5)
Requires-Dist: pandas (==1.4.4)
Requires-Dist: tqdm (==4.64.1)
